quantlab/__init__.py
quantlab/analysis/__init__.py
quantlab/analysis/greeks_calculator.py
quantlab/analysis/options_analyzer.py
quantlab/analysis/options_strategies.py
quantlab/analysis/technical_indicators.py
quantlab/backtest/__init__.py
quantlab/backtest/handlers.py
quantlab/backtest/realtime_features.py
quantlab/backtest/validators.py
quantlab/backtest/strategies/__init__.py
quantlab/backtest/strategies/mean_reversion_strategy.py
quantlab/backtest/strategies/sentiment_momentum_strategy.py
quantlab/backtest/strategies/tech_fundamental_strategy.py
quantlab/cli/__init__.py
quantlab/cli/analyze.py
quantlab/cli/data.py
quantlab/cli/lookup.py
quantlab/cli/main.py
quantlab/cli/portfolio.py
quantlab/cli/screen.py
quantlab/cli/strategy.py
quantlab/cli/visualize.py
quantlab/core/__init__.py
quantlab/core/analyzer.py
quantlab/core/portfolio_manager.py
quantlab/core/saved_screens.py
quantlab/core/screen_backtest.py
quantlab/core/screen_comparison.py
quantlab/core/screen_export.py
quantlab/core/screen_visualizer.py
quantlab/core/screen_watcher.py
quantlab/core/screener.py
quantlab/core/watchlist.py
quantlab/data/__init__.py
quantlab/data/api_clients.py
quantlab/data/data_manager.py
quantlab/data/database.py
quantlab/data/lookup_tables.py
quantlab/data/parquet_reader.py
quantlab/models/__init__.py
quantlab/models/portfolio.py
quantlab/models/ticker_data.py
quantlab/utils/__init__.py
quantlab/utils/config.py
quantlab/utils/logger.py
quantlab/visualization/__init__.py
quantlab/visualization/backtest_charts.py
quantlab/visualization/base.py
quantlab/visualization/options_charts.py
quantlab/visualization/portfolio_charts.py
quantlab/visualization/price_charts.py
quantlab/visualization/technical_charts.py
quantlabs-0.3.0.dist-info/METADATA
quantlabs-0.3.0.dist-info/WHEEL
quantlabs-0.3.0.dist-info/entry_points.txt
quantlabs-0.3.0.dist-info/licenses/LICENSE
quantlabs-0.3.0.dist-info/RECORD
