Metadata-Version: 2.4
Name: quantlabs
Version: 0.3.0
Summary: Professional quantitative trading research platform with ML-powered backtesting, multi-source options analysis, portfolio management, and interactive Plotly visualizations
Project-URL: Homepage, https://github.com/nittygritty-zzy/quantlab
Project-URL: Documentation, https://quantlabs.readthedocs.io
Project-URL: Repository, https://github.com/nittygritty-zzy/quantlab
Project-URL: Bug Tracker, https://github.com/nittygritty-zzy/quantlab/issues
Project-URL: Changelog, https://github.com/nittygritty-zzy/quantlab/releases
Author-email: nittygritty-zzy <nittygritty-zzy@users.noreply.github.com>
Maintainer-email: nittygritty-zzy <nittygritty-zzy@users.noreply.github.com>
License: MIT
License-File: LICENSE
Keywords: algorithmic-trading,backtesting,data-visualization,financial-analysis,machine-learning,options-trading,portfolio-management,qlib,quantitative-finance
Classifier: Development Status :: 3 - Alpha
Classifier: Intended Audience :: Developers
Classifier: Intended Audience :: Financial and Insurance Industry
Classifier: Intended Audience :: Science/Research
Classifier: License :: OSI Approved :: MIT License
Classifier: Operating System :: OS Independent
Classifier: Programming Language :: Python :: 3
Classifier: Programming Language :: Python :: 3.8
Classifier: Programming Language :: Python :: 3.9
Classifier: Programming Language :: Python :: 3.10
Classifier: Programming Language :: Python :: 3.11
Classifier: Topic :: Office/Business :: Financial :: Investment
Classifier: Topic :: Scientific/Engineering :: Information Analysis
Requires-Python: >=3.8
Requires-Dist: click>=8.0.0
Requires-Dist: duckdb>=0.9.0
Requires-Dist: numpy>=1.24.0
Requires-Dist: openpyxl>=3.1.5
Requires-Dist: pandas>=2.0.0
Requires-Dist: plotly>=5.18.0
Requires-Dist: polygon-api-client>=1.12.0
Requires-Dist: pyyaml>=6.0
Requires-Dist: requests>=2.31.0
Requires-Dist: scipy>=1.10.0
Requires-Dist: tabulate>=0.9.0
Requires-Dist: yfinance>=0.2.0
Provides-Extra: dev
Requires-Dist: black>=23.0.0; extra == 'dev'
Requires-Dist: myst-parser>=3.0.1; extra == 'dev'
Requires-Dist: pytest-cov>=5.0.0; extra == 'dev'
Requires-Dist: pytest>=7.0.0; extra == 'dev'
Requires-Dist: ruff>=0.1.0; extra == 'dev'
Requires-Dist: sphinx-autodoc-typehints>=2.0.1; extra == 'dev'
Requires-Dist: sphinx-rtd-theme>=3.0.2; extra == 'dev'
Requires-Dist: sphinx>=7.1.2; extra == 'dev'
Requires-Dist: sphinxcontrib-napoleon>=0.7; extra == 'dev'
